{
    "name": "phonegap-forge",
    "description": "PhoneGap Forge.",
    "version": "0.0.2",
    "homepage": "http://github.com/hermwong/phonegap-forge",
    "repository": {
        "type": "git",
        "url": "git://github.com/hermwong/phonegap-forge.git"
    },
    "keywords": [
        "phonegap"
    ],
    "preferGlobal": "false",
    "scripts": {
    },
    "devDependencies": {
        "grunt": "0.4.1",
        "grunt-node-webkit-builder": "0.1.13"
    },
    "contributors": [
        {
            "name": "Herm Wong",
            "email": "herm.wong@gmail.com"
        },
        {
            "name": "Michael Brooks",
            "email": "michael@michaelbrooks.ca",
            "url": "http://michaelbrooks.ca/"
        }
    ]
}
